<?xml version="1.0" encoding="utf-8"?>
<!DOCTYPE hibernate-mapping PUBLIC "-//Hibernate/Hibernate Mapping DTD 3.0//EN"
"http://hibernate.sourceforge.net/hibernate-mapping-3.0.dtd">
	<!--
		Mapping file autogenerated by MyEclipse Persistence Tools
	-->
<hibernate-mapping>
	<class name="org.iti.gh.entity.GhXm" table="GH_XM" schema="dbo">
		<id name="kyId" type="java.lang.Long">
			<column name="KY_ID" precision="18" scale="0" />
			<generator class="native" />
		</id>
		<property name="kyMc" type="java.lang.String">
			<column name="KY_MC" length="200" />
		</property>
		<property name="kyLy" type="java.lang.String">
			<column name="KY_LY" length="200" />
		</property>
			<property name="kyLxsj" type="java.lang.String">
			<column name="KY_LXSJ" length="50" />
		</property>
		<property name="kyKssj" type="java.lang.String">
			<column name="KY_KSSJ" length="50" />
		</property>
		<property name="kyJssj" type="java.lang.String">
			<column name="KY_JSSJ" length="50" />
		</property>
		<property name="kyJf" type="java.lang.Float">
			<column name="KY_JF" precision="53" scale="0" />
		</property>
		<property name="kyGx" type="java.lang.Integer">
			<column name="KY_GX" />
		</property>
		<property name="kyCdrw" type="java.lang.String">
			<column name="KY_CDRW" length="10" />
		</property>
		<property name="kyLx" type="java.lang.Short">
			<column name="KY_LX" not-null="true" />
		</property>
		<property name="kuId" type="java.lang.Long">
			<column name="KU_ID" precision="18" scale="0" not-null="true" />
		</property>
		<property name="yjId" type="java.lang.String">
			<column name="YJ_ID" length="20" />
		</property>
		<property name="kyNumber" type="java.lang.String">
			<column name="KY_NUMBER" length="20" />
		</property>
		<property name="kySubjetype" type="java.lang.String">
			<column name="KY_SUBJETYPE" length="10" />
		</property>
		<property name="kyProman" type="java.lang.String">
			<column name="KY_PROMAN" length="50" />
		</property>
		<property name="kyProstaffs" type="java.lang.String">
			<column name="KY_PROSTAFFS" length="500" />
		</property>
		<property name="kyRegister" type="java.lang.String">
			<column name="KY_REGISTER" length="50" />
		</property>
		<property name="kyClass" type="java.lang.String">
			<column name="KY_CLASS" length="10" />
		</property>
		<property name="kyScale" type="java.lang.String">
			<column name="KY_SCALE" length="10" />
		</property>
		<property name="kyProgress" type="java.lang.String">
			<column name="KY_PROGRESS" length="10" />
		</property>
		<property name="kyTarget" type="java.lang.String">
			<column name="KY_TARGET"  length="500"/>
		</property>
		<property name="kyIdenttime" type="java.lang.String">
			<column name="KY_IDENTTIME" length="40" />
		</property>
		<property name="kyLevel" type="java.lang.String">
			<column name="KY_LEVEL"  length="200"/>
		</property>
		<property name="kyPrize" type="java.lang.String">
			<column name="KY_PRIZE" length="10" />
		</property>
		<property name="kyHfile" type="java.lang.Short">
			<column name="KY_HFILE" />
		</property>
		<property name="auditState" type="java.lang.Short">
			<column name="AUDIT_STATE"></column>
		</property>
		<property name="auditUid" type="java.lang.Long">
			<column name="AUDIT_UID" precision="18" scale="0"></column>
		</property>
		<property name="reason" type="java.lang.String">
			<column name="AUDIT_REASON" length="500"></column>
		</property>
		
		<property name="internalNum" type="java.lang.String">
			<column name="KY_INTERNALNUM" length="100"></column>
		</property>
		<property name="kyContraNum" type="java.lang.String">
			<column name="KY_CONTRA_NUM" length="100"></column>
		</property>
		<property name="kyFinishUnit" type="java.lang.String">
			<column name="KY_FINISH_UNIT" length="100"></column>
		</property>
		<property name="kySetFinishTime" type="java.lang.String">
			<column name="KY_SET_FINISHTIME" length="50"></column>
		</property>
		<property name="kyRealFinishTime" type="java.lang.String">
			<column name="KY_REAL_FINISHTIME" length="50"></column>
		</property>
		<property name="kyGrants" type="java.lang.Float">
			<column name="KY_GRANTS" precision="53" scale="0" ></column>
		</property>
		<property name="kyContentFinishConditon" type="java.lang.String">
			<column name="KY_FINISH_CONDITION" length="200"></column>
		</property>
		<property name="kyFruit" type="java.lang.String">
			<column name="KY_FRUIT" length="200"></column>
		</property>

		<property name="commitCom" type="java.lang.String">
            <column name="Commit_Company" length="100" />
        </property>
        <property name="commitComPlace" type="java.lang.String">
             <column name="Commit_Company_Place" length="100"  />
        </property>
        <property name="acceptCom" type="java.lang.String">
            <column name="Accept_Company" length="100" />
        </property>
        <property name="acceptComPlace" type="java.lang.String">
             <column name="Accept_Company_Place" length="100"  />
        </property>
        
        <property name="contractType" type="java.lang.String">
            <column name="Contract_Type" length="50" />
        </property>
	</class>
</hibernate-mapping>
