<?xml version="1.0" encoding="utf-8"?>
<!DOCTYPE hibernate-mapping PUBLIC "-//Hibernate/Hibernate Mapping DTD 3.0//EN"
"http://hibernate.sourceforge.net/hibernate-mapping-3.0.dtd">
<!-- 
    Mapping file autogenerated by MyEclipse Persistence Tools
-->
<hibernate-mapping>
    <class name="org.iti.gh.entity.GhZcqc" table="GH_ZCQC" schema="dbo">
        <id name="zcId" type="java.lang.Long">
            <column name="ZC_ID" precision="18" scale="0" />
            <generator class="native" />
        </id>
        <property name="TId" type="java.lang.String">
            <column name="T_ID" precision="18" scale="0" />
        </property>
        <property name="zcLevel" type="java.lang.String">
            <column name="ZC_LEVEL" length="50" />
        </property>
        <property name="zcTime" type="java.lang.String">
            <column name="ZC_TIME" length="50" />
        </property>
        <property name="zcNum" type="java.lang.String">
            <column name="ZC_NUM" length="50" />
        </property>
        <property name="zcPubdept" type="java.lang.String">
            <column name="ZC_PUBDEPT" length="100" />
        </property>
        <property name="zcPubtime" type="java.lang.String">
            <column name="ZC_PUBTIME" length="50" />
        </property>
        <property name="zcQuasym" type="java.lang.String">
            <column name="ZC_QUASYM" length="100" />
        </property>
        <property name="zcIdentdept" type="java.lang.String">
            <column name="ZC_IDENTDEPT" length="100" />
        </property>
        <property name="kuId" type="java.lang.Long">
            <column name="KU_ID" precision="18" scale="0" />
        </property>
    </class>
</hibernate-mapping>
